{"_id":"5542a3e742c9161c1269dce0","round":2044,"game":4155255,"type":"draw","player1":{"id":14,"score":0.5,"color":1,"botDied":false},"player2":{"id":61,"score":0.5,"color":2,"botDied":false},"boardNotation":"s3 00, a3 04, ph 05, a3 06, p3 07, p4 12, P1 23, p2 30, P4 32, c2 34, c1 35, p3 37, P1 39, p3 40, P1 42, C1 44, C2 45, p2 47, P4 49, p3 56, P2 67, P1 72, A1 73, PH 74, A1 75, S1 79","moves":[{"move":"4536","laser":["79","69","59","49","48","47","37","38","39","29","19","09"],"killedFigure":null},{"move":"3546","laser":["00","10","20","30","31","32","42","41","40","50","60","70"],"killedFigure":null},{"move":"6777","laser":["79","69","59","49","48","47","37","38","39","29","19","09"],"killedFigure":null},{"move":"4647","laser":["00","10","20","30","31","32","42","41","40","50","60","70"],"killedFigure":null},{"move":"7364","laser":["79","69","59","49","48","47","57","67","77","78"],"killedFigure":null},{"move":"3423","laser":["00","10","20","30","31","32","42","41","40","50","60","70"],"killedFigure":null},{"move":"75-1","laser":["79","69","59","49","48","47","57","67","77","78"],"killedFigure":null},{"move":"2322","laser":["00","10","20","30","31","32","42","41","40","50","60","70"],"killedFigure":null},{"move":"3221","laser":["79","69","59","49","48","47","57","67","77","78"],"killedFigure":null},{"move":"2212","laser":["00","10","20","30","31","32","33","34","24","14"],"killedFigure":null},{"move":"3938","laser":["79","69","59","49","48","47","57","67","77","78"],"killedFigure":null},{"move":"2213","laser":["00","10","20","30","31","32","33","34","24","14"],"killedFigure":null},{"move":"2132","laser":["79","69","59","49","48","47","57","67","77","78"],"killedFigure":null},{"move":"1324","laser":["00","10","20","30","31","32","42","41","40","50","60","70"],"killedFigure":null},{"move":"4433","laser":["79","69","59","49","48","47","57","67","77","78"],"killedFigure":null},{"move":"2415","laser":["00","10","20","30","31","32","42","41","40","50","60","70"],"killedFigure":null},{"move":"7766","laser":["79","69","59","49","48","47","57","67","77"],"killedFigure":null},{"move":"1516","laser":["00","10","20","30","31","32","42","41","40","50","60","70"],"killedFigure":null},{"move":"75-1","laser":["79","69","59","49","48","47","57","67","77"],"killedFigure":null},{"move":"1617","laser":["00","10","20","30","31","32","42","41","40","50","60","70"],"killedFigure":null},{"move":"4241","laser":["79","69","59","49","48","47","57","67","77"],"killedFigure":null},{"move":"1718","laser":["00","10","20","30","31","32","42","52","62","72","71","70"],"killedFigure":null},{"move":"6453","laser":["79","69","59","49","48","47","57","67","77"],"killedFigure":null},{"move":"40-1","laser":["00","10","20","30","31","32","42","52","62","72","71","70"],"killedFigure":null},{"move":"3646","laser":["79","69","59","49","48","47","57","67","77"],"killedFigure":null},{"move":"0415","laser":["00","10","20","30","31","32","42","52","62","72","71","70"],"killedFigure":null},{"move":"6676","laser":["79","69","59","49","48","47","57","67","77"],"killedFigure":null},{"move":"0514","laser":["00","10","20","30","31","32","42","52","62","72","71","70"],"killedFigure":null},{"move":"76-1","laser":["79","69","59","49","48","47","57","67","77"],"killedFigure":null},{"move":"0605","laser":["00","10","20","30","31","32","42","52","62","72","71","70"],"killedFigure":null},{"move":"76+1","laser":["79","69","59","49","48","47","57","67","77"],"killedFigure":null},{"move":"0504","laser":["00","10","20","30","31","32","42","52","62","72","71","70"],"killedFigure":null},{"move":"3334","laser":["79","69","59","49","48","47","57","67","77"],"killedFigure":null},{"move":"0403","laser":["00","10","20","30","31","32","42","52","62","72","71","70"],"killedFigure":null},{"move":"5363","laser":["79","69","59","49","48","47","57","67","77"],"killedFigure":null},{"move":"0302","laser":["00","10","20","30","31","32","42","52","62","72","71","70"],"killedFigure":null},{"move":"6364","laser":["79","69","59","49","48","47","57","67","77"],"killedFigure":null},{"move":"0211","laser":["00","10","20","30","31","32","42","52","62","72","71","70"],"killedFigure":null},{"move":"79-1","laser":["79","78","77","76","66","56","57","58","59"],"killedFigure":null},{"move":"3627","laser":["00","10","20","30","31","32","42","52","62","72","71","70"],"killedFigure":null},{"move":"3231","laser":["79","78","77","76","66","56","57","58","59"],"killedFigure":null},{"move":"30-1","laser":["00","10","20","30"],"killedFigure":null},{"move":"7465","laser":["79","78","77","76","66","56","57","58","59"],"killedFigure":null},{"move":"1828","laser":["00","10","20","30"],"killedFigure":null},{"move":"4655","laser":["79","78","77","76","66","56","57","58","59"],"killedFigure":null},{"move":"15+1","laser":["00","10","20","30"],"killedFigure":null},{"move":"79+1","laser":["79","69","59","49","48","47","57","67","77"],"killedFigure":null},{"move":"2817","laser":["00","10","20","30"],"killedFigure":null},{"move":"3142","laser":["79","69","59","49","48","47","57","67","77"],"killedFigure":null},{"move":"1525","laser":["00","10","20","30"],"killedFigure":null},{"move":"3444","laser":["79","69","59","49","48","47","57","67","77"],"killedFigure":null},{"move":"17-1","laser":["00","10","20","30"],"killedFigure":null},{"move":"6554","laser":["79","69","59","49","48","47","57","67","77"],"killedFigure":null},{"move":"17+1","laser":["00","10","20","30"],"killedFigure":null},{"move":"54+1","laser":["79","69","59","49","48","47","57","67","77"],"killedFigure":null},{"move":"17+1","laser":["00","10","20","30"],"killedFigure":null},{"move":"49-1","laser":["79","69","59","49"],"killedFigure":null},{"move":"1726","laser":["00","10","20","30"],"killedFigure":null},{"move":"4232","laser":["79","69","59","49"],"killedFigure":null},{"move":"2515","laser":["00","10","20","30"],"killedFigure":null},{"move":"75+1","laser":["79","69","59","49"],"killedFigure":null},{"move":"1504","laser":["00","10","20","30"],"killedFigure":null},{"move":"76-1","laser":["79","69","59","49"],"killedFigure":null},{"move":"1415","laser":["00","10","20","30"],"killedFigure":null},{"move":"5445","laser":["79","69","59","49"],"killedFigure":null},{"move":"1506","laser":["00","10","20","30"],"killedFigure":null},{"move":"6463","laser":["79","69","59","49"],"killedFigure":null},{"move":"1202","laser":["00","10","20","30"],"killedFigure":null},{"move":"3243","laser":["79","69","59","49"],"killedFigure":null},{"move":"2617","laser":["00","10","20","30"],"killedFigure":null},{"move":"3848","laser":["79","69","59","49"],"killedFigure":null},{"move":"2716","laser":["00","10","20","30"],"killedFigure":null},{"move":"4151","laser":["79","69","59","49"],"killedFigure":null},{"move":"16-1","laser":["00","10","20","30"],"killedFigure":null},{"move":"7564","laser":["79","69","59","49"],"killedFigure":null},{"move":"16+1","laser":["00","10","20","30"],"killedFigure":null},{"move":"4958","laser":["79","69","59","49","39","29","19","09"],"killedFigure":null},{"move":"1605","laser":["00","10","20","30"],"killedFigure":null},{"move":"48+1","laser":["79","69","59","49","39","29","19","09"],"killedFigure":null},{"move":"1727","laser":["00","10","20","30"],"killedFigure":null},{"move":"7261","laser":["79","69","59","49","39","29","19","09"],"killedFigure":null},{"move":"1122","laser":["00","10","20","30"],"killedFigure":null},{"move":"48-1","laser":["79","69","59","49","39","29","19","09"],"killedFigure":null},{"move":"2221","laser":["00","10","20","30"],"killedFigure":null},{"move":"6374","laser":["79","69","59","49","39","29","19","09"],"killedFigure":null},{"move":"2132","laser":["00","10","20","30"],"killedFigure":null},{"move":"3334","laser":["79","69","59","49","39","29","19","09"],"killedFigure":null},{"move":"27+1","laser":["00","10","20","30"],"killedFigure":null},{"move":"7463","laser":["79","69","59","49","39","29","19","09"],"killedFigure":null},{"move":"2728","laser":["00","10","20","30"],"killedFigure":null},{"move":"7667","laser":["79","69","59","49","39","29","19","09"],"killedFigure":null},{"move":"3031","laser":["00","10","20","30","40","41","42","43","53"],"killedFigure":null},{"move":"3435","laser":["79","69","59","49","39","29","19","09"],"killedFigure":null},{"move":"3142","laser":["00","10","20","30","40","41","42"],"killedFigure":null},{"move":"4443","laser":["79","69","59","49","39","29","19","09"],"killedFigure":null},{"move":"28-1","laser":["00","10","20","30","40","41","42"],"killedFigure":null},{"move":"5869","laser":["79","69"],"killedFigure":null},{"move":"2817","laser":["00","10","20","30","40","41","42"],"killedFigure":null},{"move":"4342","laser":["79","69"],"killedFigure":null},{"move":"17-1","laser":["00","10","20","30","40","41","42"],"killedFigure":null},{"move":"4453","laser":["79","69"],"killedFigure":null},{"move":"17+1","laser":["00","10","20","30","40","41","42"],"killedFigure":null},{"move":"35+1","laser":["79","69"],"killedFigure":null},{"move":"17+1","laser":["00","10","20","30","40","41","42"],"killedFigure":null},{"move":"6162","laser":["79","69"],"killedFigure":null},{"move":"3222","laser":["00","10","20","30","40","41","42","32"],"killedFigure":null},{"move":"3546","laser":["79","69"],"killedFigure":null},{"move":"2223","laser":["00","10","20","30","40","41","42","32","22","12","02","01"],"killedFigure":null},{"move":"79-1","laser":["79","78","77","76","75","74","73","72","71","70"],"killedFigure":null},{"move":"0516","laser":["00","10","20","30","40","41","42","32","22","12","02","01"],"killedFigure":null},{"move":"64+1","laser":["79","78","77","76","75","74","73","72","71","70"],"killedFigure":null},{"move":"0405","laser":["00","10","20","30","40","41","42","32","22","12","02","01"],"killedFigure":null},{"move":"4859","laser":["79","78","77","76","75","74","73","72","71","70"],"killedFigure":null},{"move":"3727","laser":["00","10","20","30","40","41","42","32","22","12","02","01"],"killedFigure":null},{"move":"62-1","laser":["79","78","77","76","75","74","73","72","71","70"],"killedFigure":null},{"move":"2728","laser":["00","10","20","30","40","41","42","32","22","12","02","01"],"killedFigure":null},{"move":"5968","laser":["79","78","77","76","75","74","73","72","71","70"],"killedFigure":null},{"move":"28-1","laser":["00","10","20","30","40","41","42","32","22","12","02","01"],"killedFigure":null},{"move":"53-1","laser":["79","78","77","76","75","74","73","72","71","70"],"killedFigure":null},{"move":"4050","laser":["00","10","20","30","40","50","51","41","31","21","11","01"],"killedFigure":null},{"move":"63+1","laser":["79","78","77","76","75","74","73","72","71","70"],"killedFigure":null},{"move":"2818","laser":["00","10","20","30","40","50","51","41","31","21","11","01"],"killedFigure":null},{"move":"5354","laser":["79","78","77","76","75","74","73","72","71","70"],"killedFigure":null},{"move":"4353","laser":["00","10","20","30","40","50","51","41","31","21","11","01"],"killedFigure":null},{"move":"6757","laser":["79","78","77","76","75","74","73","72","71","70"],"killedFigure":null},{"move":"5040","laser":["00","10","20","30","40","41","42","32","22","12","02","01"],"killedFigure":null},{"move":"5444","laser":["79","78","77","76","75","74","73","72","71","70"],"killedFigure":null},{"move":"23-1","laser":["00","10","20","30","40","41","42","32","22","12","02","01"],"killedFigure":null},{"move":"64-1","laser":["79","78","77","76","75","74","73","72","71","70"],"killedFigure":null},{"move":"40-1","laser":["00","10","20","30","40"],"killedFigure":null},{"move":"68+1","laser":["79","78","77","76","75","74","73","72","71","70"],"killedFigure":null},{"move":"1827","laser":["00","10","20","30","40"],"killedFigure":null},{"move":"5767","laser":["79","78","77","76","75","74","73","72","71","70"],"killedFigure":null},{"move":"40+1","laser":["00","10","20","30","40","41","42","32","22","12","02","01"],"killedFigure":null},{"move":"6465","laser":["79","78","77","76","75","74","73","72","71","70"],"killedFigure":null},{"move":"4030","laser":["00","10","20","30","31","32","33","34","35","36","37","38","39"],"killedFigure":null},{"move":"6352","laser":["79","78","77","76","75","74","73","72","71","70"],"killedFigure":null},{"move":"53-1","laser":["00","10","20","30","31","32","33","34","35","36","37","38","39"],"killedFigure":null},{"move":"5546","laser":["79","78","77","76","75","74","73","72","71","70"],"killedFigure":null},{"move":"3041","laser":["00","10","20","30","40","50","60","70"],"killedFigure":null},{"move":"62+1","laser":["79","78","77","76","75","74","73","72","71","70"],"killedFigure":null},{"move":"41-1","laser":["00","10","20","30","40","50","60","70"],"killedFigure":null},{"move":"67+1","laser":["79","78","77","76","75","74","73","72","71","70"],"killedFigure":null},{"move":"41+1","laser":["00","10","20","30","40","50","60","70"],"killedFigure":null},{"move":"6757","laser":["79","78","77","76","75","74","73","72","71","70"],"killedFigure":null},{"move":"41-1","laser":["00","10","20","30","40","50","60","70"],"killedFigure":null},{"move":"5161","laser":["79","78","77","76","75","74","73","72","71","70"],"killedFigure":null},{"move":"4132","laser":["00","10","20","30","40","50","60","70"],"killedFigure":null},{"move":"4637","laser":["79","78","77","76","75","74","73","72","71","70"],"killedFigure":null},{"move":"3233","laser":["00","10","20","30","40","50","60","70"],"killedFigure":null},{"move":"45-1","laser":["79","78","77","76","75","74","73","72","71","70"],"killedFigure":null},{"move":"3334","laser":["00","10","20","30","40","50","60","70"],"killedFigure":null},{"move":"37-1","laser":["79","78","77","76","75","74","73","72","71","70"],"killedFigure":null},{"move":"3425","laser":["00","10","20","30","40","50","60","70"],"killedFigure":null},{"move":"3726","laser":["79","78","77","76","75","74","73","72","71","70"],"killedFigure":null},{"move":"2737","laser":["00","10","20","30","40","50","60","70"],"killedFigure":null},{"move":"4433","laser":["79","78","77","76","75","74","73","72","71","70"],"killedFigure":null},{"move":"37+1","laser":["00","10","20","30","40","50","60","70"],"killedFigure":null},{"move":"45-1","laser":["79","78","77","76","75","74","73","72","71","70"],"killedFigure":null},{"move":"3728","laser":["00","10","20","30","40","50","60","70"],"killedFigure":null},{"move":"3324","laser":["79","78","77","76","75","74","73","72","71","70"],"killedFigure":null},{"move":"25-1","laser":["00","10","20","30","40","50","60","70"],"killedFigure":null},{"move":"4232","laser":["79","78","77","76","75","74","73","72","71","70"],"killedFigure":null},{"move":"2837","laser":["00","10","20","30","40","50","60","70"],"killedFigure":null},{"move":"3223","laser":["79","78","77","76","75","74","73","72","71","70"],"killedFigure":null},{"move":"3243","laser":["00","10","20","30","40","50","60","70"],"killedFigure":null},{"move":"2322","laser":["79","78","77","76","75","74","73","72","71","70"],"killedFigure":null},{"move":"43+1","laser":["00","10","20","30","40","50","60","70"],"killedFigure":null},{"move":"5263","laser":["79","78","77","76","75","74","73","72","71","70"],"killedFigure":null},{"move":"4333","laser":["00","10","20","30","40","50","60","70"],"killedFigure":null},{"move":"2413","laser":["79","78","77","76","75","74","73","72","71","70"],"killedFigure":null},{"move":"3728","laser":["00","10","20","30","40","50","60","70"],"killedFigure":null},{"move":"13-1","laser":["79","78","77","76","75","74","73","72","71","70"],"killedFigure":null},{"move":"33+1","laser":["00","10","20","30","40","50","60","70"],"killedFigure":null},{"move":"6959","laser":["79","78","77","76","75","74","73","72","71","70"],"killedFigure":null},{"move":"3343","laser":["00","10","20","30","40","50","60","70"],"killedFigure":null},{"move":"1314","laser":["79","78","77","76","75","74","73","72","71","70"],"killedFigure":null},{"move":"4757","laser":["00","10","20","30","40","50","60","70"],"killedFigure":null},{"move":"2627","laser":["79","78","77","76","75","74","73","72","71","70"],"killedFigure":null},{"move":"5364","laser":["00","10","20","30","40","50","60","70"],"killedFigure":null},{"move":"6374","laser":["79","78","77","76","75"],"killedFigure":null},{"move":"2838","laser":["00","10","20","30","40","50","60","70"],"killedFigure":null},{"move":"2728","laser":["79","78","77","76","75"],"killedFigure":null},{"move":"25-1","laser":["00","10","20","30","40","50","60","70"],"killedFigure":null},{"move":"1423","laser":["79","78","77","76","75"],"killedFigure":null},{"move":"2526","laser":["00","10","20","30","40","50","60","70"],"killedFigure":null},{"move":"4748","laser":["79","78","77","76","75"],"killedFigure":null},{"move":"3847","laser":["00","10","20","30","40","50","60","70"],"killedFigure":null},{"move":"59+1","laser":["79","78","77","76","75"],"killedFigure":null},{"move":"2615","laser":["00","10","20","30","40","50","60","70"],"killedFigure":null},{"move":"6151","laser":["79","78","77","76","75"],"killedFigure":null},{"move":"17+1","laser":["00","10","20","30","40","50","60","70"],"killedFigure":null},{"move":"2817","laser":["79","78","77","76","75"],"killedFigure":null},{"move":"4332","laser":["00","10","20","30","40","50","60","70"],"killedFigure":null},{"move":"4535","laser":["79","78","77","76","75"],"killedFigure":null},{"move":"28+1","laser":["00","10","20","30","40","50","60","70"],"killedFigure":null},{"move":"3525","laser":["79","78","77","76","75"],"killedFigure":null},{"move":"4746","laser":["00","10","20","30","40","50","60","70"],"killedFigure":null},{"move":"2526","laser":["79","78","77","76","75"],"killedFigure":null},{"move":"4637","laser":["00","10","20","30","40","50","60","70"],"killedFigure":null},{"move":"5544","laser":["79","78","77","76","75"],"killedFigure":null},{"move":"3243","laser":["00","10","20","30","40","50","60","70"],"killedFigure":null},{"move":"6554","laser":["79","78","77","76","75"],"killedFigure":null},{"move":"3736","laser":["00","10","20","30","40","50","60","70"],"killedFigure":null},{"move":"6272","laser":["79","78","77","76","75"],"killedFigure":null},{"move":"3627","laser":["00","10","20","30","40","50","60","70"],"killedFigure":null},{"move":"54+1","laser":["79","78","77","76","75"],"killedFigure":null},{"move":"4342","laser":["00","10","20","30","40","50","60","70"],"killedFigure":null},{"move":"2313","laser":["79","78","77","76","75"],"killedFigure":null},{"move":"4252","laser":["00","10","20","30","40","50","60","70"],"killedFigure":null},{"move":"1324","laser":["79","78","77","76","75"],"killedFigure":null},{"move":"5253","laser":["00","10","20","30","40","50","60","70"],"killedFigure":null},{"move":"17+1","laser":["79","78","77","76","75"],"killedFigure":null},{"move":"5666","laser":["00","10","20","30","40","50","60","70"],"killedFigure":null},{"move":"48+1","laser":["79","78","77","76","75"],"killedFigure":null},{"move":"5343","laser":["00","10","20","30","40","50","60","70"],"killedFigure":null},{"move":"5949","laser":["79","78","77","76","75"],"killedFigure":null},{"move":"43+1","laser":["00","10","20","30","40","50","60","70"],"killedFigure":null},{"move":"49+1","laser":["79","78","77","76","75"],"killedFigure":null},{"move":"2818","laser":["00","10","20","30","40","50","60","70"],"killedFigure":null},{"move":"2636","laser":["79","78","77","76","75"],"killedFigure":null},{"move":"2738","laser":["00","10","20","30","40","50","60","70"],"killedFigure":null},{"move":"4859","laser":["79","78","77","76","75"],"killedFigure":null},{"move":"3847","laser":["00","10","20","30","40","50","60","70"],"killedFigure":null},{"move":"1726","laser":["79","78","77","76","75"],"killedFigure":null},{"move":"1827","laser":["00","10","20","30","40","50","60","70"],"killedFigure":null},{"move":"6869","laser":["79","78","77","76","75"],"killedFigure":null},{"move":"2717","laser":["00","10","20","30","40","50","60","70"],"killedFigure":null},{"move":"5463","laser":["79","78","77","76","75"],"killedFigure":null},{"move":"4332","laser":["00","10","20","30","40","50","60","70"],"killedFigure":null},{"move":"24-1","laser":["79","78","77","76","75"],"killedFigure":null},{"move":"17-1","laser":["00","10","20","30","40","50","60","70"],"killedFigure":null},{"move":"6352","laser":["79","78","77","76","75"],"killedFigure":null},{"move":"17-1","laser":["00","10","20","30","40","50","60","70"],"killedFigure":null},{"move":"5253","laser":["79","78","77","76","75"],"killedFigure":null},{"move":"17-1","laser":["00","10","20","30","40","50","60","70"],"killedFigure":null},{"move":"69+1","laser":["79","78","77","76","75"],"killedFigure":null},{"move":"17-1","laser":["00","10","20","30","40","50","60","70"],"killedFigure":null},{"move":"36+1","laser":["79","78","77","76","75"],"killedFigure":null},{"move":"17-1","laser":["00","10","20","30","40","50","60","70"],"killedFigure":null},{"move":"2221","laser":["79","78","77","76","75"],"killedFigure":null},{"move":"3231","laser":["00","10","20","30","40","50","60","70"],"killedFigure":null},{"move":"49+1","laser":["79","78","77","76","75"],"killedFigure":null},{"move":"3122","laser":["00","10","20","30","40","50","60","70"],"killedFigure":null},{"move":"2131","laser":["79","78","77","76","75"],"killedFigure":null},{"move":"2213","laser":["00","10","20","30","40","50","60","70"],"killedFigure":null},{"move":"53-1","laser":["79","78","77","76","75"],"killedFigure":null},{"move":"1727","laser":["00","10","20","30","40","50","60","70"],"killedFigure":null},{"move":"4958","laser":["79","78","77","76","75"],"killedFigure":null},{"move":"2737","laser":["00","10","20","30","40","50","60","70"],"killedFigure":null},{"move":"5363","laser":["79","78","77","76","75"],"killedFigure":null},{"move":"16-1","laser":["00","10","20","30","40","50","60","70"],"killedFigure":null},{"move":"7271","laser":["79","78","77","76","75"],"killedFigure":null},{"move":"16-1","laser":["00","10","20","30","40","50","60","70"],"killedFigure":null},{"move":"5849","laser":["79","78","77","76","75"],"killedFigure":null},{"move":"1617","laser":["00","10","20","30","40","50","60","70"],"killedFigure":null},{"move":"59+1","laser":["79","78","77","76","75"],"killedFigure":null},{"move":"15-1","laser":["00","10","20","30","40","50","60","70"],"killedFigure":null},{"move":"2434","laser":["79","78","77","76","75"],"killedFigure":null},{"move":"1516","laser":["00","10","20","30","40","50","60","70"],"killedFigure":null},{"move":"2637","laser":["79","78","77","76","75"],"killedFigure":null},{"move":"1728","laser":["00","10","20","30","40","50","60","70"],"killedFigure":null},{"move":"7473","laser":["79","78","77","76","75","74"],"killedFigure":null},{"move":"1615","laser":["00","10","20","30","40","50","60","70"],"killedFigure":null},{"move":"3746","laser":["79","78","77","76","75","74"],"killedFigure":null},{"move":"1525","laser":["00","10","20","30","40","50","60","70"],"killedFigure":null},{"move":"3121","laser":["79","78","77","76","75","74"],"killedFigure":null},{"move":"2535","laser":["00","10","20","30","40","50","60","70"],"killedFigure":null},{"move":"5968","laser":["79","78","77","76","75","74"],"killedFigure":null},{"move":"2625","laser":["00","10","20","30","40","50","60","70"],"killedFigure":null},{"move":"68-1","laser":["79","78","77","76","75","74"],"killedFigure":null},{"move":"2514","laser":["00","10","20","30","40","50","60","70"],"killedFigure":null},{"move":"4939","laser":["79","78","77","76","75","74"],"killedFigure":null},{"move":"1415","laser":["00","10","20","30","40","50","60","70"],"killedFigure":null},{"move":"7162","laser":["79","78","77","76","75","74"],"killedFigure":null},{"move":"1526","laser":["00","10","20","30","40","50","60","70"],"killedFigure":null},{"move":"6261","laser":["79","78","77","76","75","74"],"killedFigure":null},{"move":"2625","laser":["00","10","20","30","40","50","60","70"],"killedFigure":null},{"move":"4645","laser":["79","78","77","76","75","74"],"killedFigure":null},{"move":"2514","laser":["00","10","20","30","40","50","60","70"],"killedFigure":null},{"move":"4433","laser":["79","78","77","76","75","74"],"killedFigure":null},{"move":"1424","laser":["00","10","20","30","40","50","60","70"],"killedFigure":null},{"move":"3443","laser":["79","78","77","76","75","74"],"killedFigure":null},{"move":"13+1","laser":["00","10","20","30","40","50","60","70"],"killedFigure":null},{"move":"4344","laser":["79","78","77","76","75","74"],"killedFigure":null},{"move":"2423","laser":["00","10","20","30","40","50","60","70"],"killedFigure":null},{"move":"33+1","laser":["79","78","77","76","75","74"],"killedFigure":null},{"move":"13-1","laser":["00","10","20","30","40","50","60","70"],"killedFigure":null},{"move":"79+1","laser":["79","69"],"killedFigure":null},{"move":"2332","laser":["00","10","20","30","40","50","60","70"],"killedFigure":null},{"move":"44+1","laser":["79","69"],"killedFigure":null},{"move":"2827","laser":["00","10","20","30","40","50","60","70"],"killedFigure":null},{"move":"6354","laser":["79","69"],"killedFigure":null},{"move":"2737","laser":["00","10","20","30","40","50","60","70"],"killedFigure":null},{"move":"4443","laser":["79","69"],"killedFigure":null},{"move":"3242","laser":["00","10","20","30","40","50","60","70"],"killedFigure":null},{"move":"33+1","laser":["79","69"],"killedFigure":null},{"move":"3546","laser":["00","10","20","30","40","50","60","70"],"killedFigure":null},{"move":"36+1","laser":["79","69"],"killedFigure":null},{"move":"3728","laser":["00","10","20","30","40","50","60","70"],"killedFigure":null},{"move":"68+1","laser":["79","69"],"killedFigure":null},{"move":"2817","laser":["00","10","20","30","40","50","60","70"],"killedFigure":null},{"move":"3637","laser":["79","69"],"killedFigure":null},{"move":"1716","laser":["00","10","20","30","40","50","60","70"],"killedFigure":null},{"move":"37-1","laser":["79","69"],"killedFigure":null},{"move":"16+1","laser":["00","10","20","30","40","50","60","70"],"killedFigure":null},{"move":"73-1","laser":["79","69"],"killedFigure":null},{"move":"16+1","laser":["00","10","20","30","40","50","60","70"],"killedFigure":null},{"move":"4353","laser":["79","69"],"killedFigure":null},{"move":"1617","laser":["00","10","20","30","40","50","60","70"],"killedFigure":null},{"move":"5363","laser":["79","69"],"killedFigure":null},{"move":"1718","laser":["00","10","20","30","40","50","60","70"],"killedFigure":null},{"move":"33+1","laser":["79","69"],"killedFigure":null},{"move":"18+1","laser":["00","10","20","30","40","50","60","70"],"killedFigure":null},{"move":"3728","laser":["79","69"],"killedFigure":null},{"move":"18-1","laser":["00","10","20","30","40","50","60","70"],"killedFigure":null},{"move":"6877","laser":["79","69"],"killedFigure":null},{"move":"18-1","laser":["00","10","20","30","40","50","60","70"],"killedFigure":null},{"move":"28+1","laser":["79","69"],"killedFigure":null},{"move":"18-1","laser":["00","10","20","30","40","50","60","70"],"killedFigure":null},{"move":"63+1","laser":["79","69"],"killedFigure":null},{"move":"18-1","laser":["00","10","20","30","40","50","60","70"],"killedFigure":null},{"move":"2827","laser":["79","69"],"killedFigure":null},{"move":"18-1","laser":["00","10","20","30","40","50","60","70"],"killedFigure":null},{"move":"7776","laser":["79","69"],"killedFigure":null},{"move":"18+1","laser":["00","10","20","30","40","50","60","70"],"killedFigure":null},{"move":"6152","laser":["79","69"],"killedFigure":null},{"move":"18-1","laser":["00","10","20","30","40","50","60","70"],"killedFigure":null},{"move":"73-1","laser":["79","69"],"killedFigure":null},{"move":"18-1","laser":["00","10","20","30","40","50","60","70"],"killedFigure":null},{"move":"45+1","laser":["79","69"],"killedFigure":null},{"move":"18-1","laser":["00","10","20","30","40","50","60","70"],"killedFigure":null},{"move":"21-1","laser":["79","69"],"killedFigure":null},{"move":"18+1","laser":["00","10","20","30","40","50","60","70"],"killedFigure":null},{"move":"6362","laser":["79","69"],"killedFigure":null},{"move":"18-1","laser":["00","10","20","30","40","50","60","70"],"killedFigure":null},{"move":"3343","laser":["79","69"],"killedFigure":null},{"move":"4253","laser":["00","10","20","30","40","50","60","70"],"killedFigure":null},{"move":"52+1","laser":["79","69"],"killedFigure":null},{"move":"4637","laser":["00","10","20","30","40","50","60","70"],"killedFigure":null},{"move":"5465","laser":["79","69"],"killedFigure":null},{"move":"3736","laser":["00","10","20","30","40","50","60","70"],"killedFigure":null},{"move":"5242","laser":["79","69"],"killedFigure":null},{"move":"3635","laser":["00","10","20","30","40","50","60","70"],"killedFigure":null},{"move":"2132","laser":["79","69"],"killedFigure":null},{"move":"18+1","laser":["00","10","20","30","40","50","60","70"],"killedFigure":null},{"move":"62+1","laser":["79","69"],"killedFigure":null},{"move":"18+1","laser":["00","10","20","30","40","50","60","70"],"killedFigure":null},{"move":"3242","laser":["79","69"],"killedFigure":null},{"move":"18+1","laser":["00","10","20","30","40","50","60","70"],"killedFigure":null},{"move":"3231","laser":["79","69"],"killedFigure":null},{"move":"18+1","laser":["00","10","20","30","40","50","60","70"],"killedFigure":null},{"move":"7675","laser":["79","69"],"killedFigure":null},{"move":"18-1","laser":["00","10","20","30","40","50","60","70"],"killedFigure":null},{"move":"27+1","laser":["79","69"],"killedFigure":null},{"move":"18-1","laser":["00","10","20","30","40","50","60","70"],"killedFigure":null},{"move":"42+1","laser":["79","69"],"killedFigure":null},{"move":"18+1","laser":["00","10","20","30","40","50","60","70"],"killedFigure":null},{"move":"6959","laser":["79","69","59"],"killedFigure":null},{"move":"1808","laser":["00","10","20","30","40","50","60","70"],"killedFigure":null},{"move":"6554","laser":["79","69","59"],"killedFigure":null},{"move":"13-1","laser":["00","10","20","30","40","50","60","70"],"killedFigure":null},{"move":"5455","laser":["79","69","59"],"killedFigure":null},{"move":"13+1","laser":["00","10","20","30","40","50","60","70"],"killedFigure":null},{"move":"5546","laser":["79","69","59"],"killedFigure":null},{"move":"13+1","laser":["00","10","20","30","40","50","60","70"],"killedFigure":null},{"move":"4231","laser":["79","69","59"],"killedFigure":null},{"move":"3534","laser":["00","10","20","30","40","50","60","70"],"killedFigure":null},{"move":"6261","laser":["79","69","59"],"killedFigure":null},{"move":"3444","laser":["00","10","20","30","40","50","60","70"],"killedFigure":null},{"move":"3929","laser":["79","69","59"],"killedFigure":null},{"move":"4454","laser":["00","10","20","30","40","50","60","70"],"killedFigure":null},{"move":"2726","laser":["79","69","59"],"killedFigure":null},{"move":"53+1","laser":["00","10","20","30","40","50","60","70"],"killedFigure":null},{"move":"59+1","laser":["79","69","59","58","57","67","77"],"killedFigure":null},{"move":"4748","laser":["00","10","20","30","40","50","60","70"],"killedFigure":null},{"move":"45+1","laser":["79","69","59","58","57","67","77"],"killedFigure":null},{"move":"53+1","laser":["00","10","20","30","40","50","60","70"],"killedFigure":null},{"move":"2637","laser":["79","69","59","58","57","67","77"],"killedFigure":null},{"move":"5444","laser":["00","10","20","30","40","50","60","70"],"killedFigure":null},{"move":"73-1","laser":["79","69","59","58","57","67","77"],"killedFigure":null},{"move":"5363","laser":["00","10","20","30","40","50","60","70"],"killedFigure":null},{"move":"45-1","laser":["79","69","59","58","57","67","77"],"killedFigure":null},{"move":"4435","laser":["00","10","20","30","40","50","60","70"],"killedFigure":null},{"move":"4332","laser":["79","69","59","58","57","67","77"],"killedFigure":null},{"move":"3536","laser":["00","10","20","30","40","50","60","70"],"killedFigure":null},{"move":"7576","laser":["79","69","59","58","57","67","77"],"killedFigure":null},{"move":"3626","laser":["00","10","20","30","40","50","60","70"],"killedFigure":null},{"move":"45-1","laser":["79","69","59","58","57","67","77"],"killedFigure":null},{"move":"2627","laser":["00","10","20","30","40","50","60","70"],"killedFigure":null},{"move":"4555","laser":["79","69","59","58","57","67","77"],"killedFigure":null},{"move":"2716","laser":["00","10","20","30","40","50","60","70"],"killedFigure":null},{"move":"7374","laser":["79","69","59","58","57","67","77"],"killedFigure":null},{"move":"5766","laser":["00","10","20","30","40","50","60","70"],"killedFigure":null},{"move":"3726","laser":["79","69","59","58","57","67","77"],"killedFigure":null},{"move":"0817","laser":["00","10","20","30","40","50","60","70"],"killedFigure":null},{"move":"7665","laser":["79","69","59","58","57","67","77"],"killedFigure":null},{"move":"63+1","laser":["00","10","20","30","40","50","60","70"],"killedFigure":null},{"move":"4645","laser":["79","69","59","58","57","67","77"],"killedFigure":null},{"move":"6353","laser":["00","10","20","30","40","50","60","70"],"killedFigure":null},{"move":"3121","laser":["79","69","59","58","57","67","77"],"killedFigure":null},{"move":"5343","laser":["00","10","20","30","40","50","60","70"],"killedFigure":null},{"move":"2131","laser":["79","69","59","58","57","67","77"],"killedFigure":null},{"move":"48-1","laser":["00","10","20","30","40","50","60","70"],"killedFigure":null},{"move":"2627","laser":["79","69","59","58","57","67","77"],"killedFigure":null},{"move":"4352","laser":["00","10","20","30","40","50","60","70"],"killedFigure":null},{"move":"65-1","laser":["79","69","59","58","57","67","77"],"killedFigure":null},{"move":"5263","laser":["00","10","20","30","40","50","60","70"],"killedFigure":null},{"move":"3241","laser":["79","69","59","58","57","67","77"],"killedFigure":null},{"move":"6354","laser":["00","10","20","30","40","50","60","70"],"killedFigure":null},{"move":"2939","laser":["79","69","59","58","57","67","77"],"killedFigure":null},{"move":"48+1","laser":["00","10","20","30","40","50","60","70"],"killedFigure":null},{"move":"51+1","laser":["79","69","59","58","57","67","77"],"killedFigure":null},{"move":"64-1","laser":["00","10","20","30","40","50","60","70"],"killedFigure":null},{"move":"61-1","laser":["79","69","59","58","57","67","77"],"killedFigure":null},{"move":"6453","laser":["00","10","20","30","40","50","60","70"],"killedFigure":null},{"move":"4243","laser":["79","69","59","58","57","67","77"],"killedFigure":null},{"move":"53-1","laser":["00","10","20","30","40","50","60","70"],"killedFigure":null},{"move":"39+1","laser":["79","69","59","58","57","67","77"],"killedFigure":null},{"move":"5352","laser":["00","10","20","30","40","50","60","70"],"killedFigure":null},{"move":"59-1","laser":["79","69","59"],"killedFigure":null},{"move":"5242","laser":["00","10","20","30","40","50","60","70"],"killedFigure":null},{"move":"3122","laser":["79","69","59"],"killedFigure":null},{"move":"17-1","laser":["00","10","20","30","40","50","60","70"],"killedFigure":null},{"move":"39-1","laser":["79","69","59"],"killedFigure":null},{"move":"4253","laser":["00","10","20","30","40","50","60","70"],"killedFigure":null},{"move":"2211","laser":["79","69","59"],"killedFigure":null},{"move":"5363","laser":["00","10","20","30","40","50","60","70"],"killedFigure":null},{"move":"41-1","laser":["79","69","59"],"killedFigure":null},{"move":"4838","laser":["00","10","20","30","40","50","60","70"],"killedFigure":null},{"move":"5565","laser":["79","69","59"],"killedFigure":null},{"move":"00-1","laser":["00","01","02","12","22","32","42","52","62","72"],"killedFigure":null},{"move":"1101","laser":["79","69","59"],"killedFigure":null},{"move":"0212","laser":["00","01"],"killedFigure":null},{"move":"41-1","laser":["79","69","59"],"killedFigure":null},{"move":"0504","laser":["00","01"],"killedFigure":null},{"move":"4152","laser":["79","69","59"],"killedFigure":null},{"move":"0403","laser":["00","01"],"killedFigure":null},{"move":"2728","laser":["79","69","59"],"killedFigure":null},{"move":"0302","laser":["00","01"],"killedFigure":null},{"move":"7464","laser":["79","69","59"],"killedFigure":null},{"move":"5746","laser":["00","01"],"killedFigure":null},{"move":"79-1","laser":["79","78","77","76","75","74","73","72","71","70"],"killedFigure":null},{"move":"6677","laser":["00","01"],"killedFigure":null},{"move":"28-1","laser":["79","78","77"],"killedFigure":null},{"move":"17+1","laser":["00","01"],"killedFigure":null},{"move":"4344","laser":["79","78","77"],"killedFigure":null},{"move":"17+1","laser":["00","01"],"killedFigure":null},{"move":"6172","laser":["79","78","77"],"killedFigure":null},{"move":"1726","laser":["00","01"],"killedFigure":null},{"move":"6473","laser":["79","78","77"],"killedFigure":null},{"move":"1605","laser":["00","01"],"killedFigure":null},{"move":"5242","laser":["79","78","77"],"killedFigure":null},{"move":"1323","laser":["00","01"],"killedFigure":null},{"move":"4243","laser":["79","78","77"],"killedFigure":null},{"move":"2332","laser":["00","01"],"killedFigure":null},{"move":"4536","laser":["79","78","77"],"killedFigure":null},{"move":"2625","laser":["00","01"],"killedFigure":null},{"move":"73+1","laser":["79","78","77"],"killedFigure":null},{"move":"2524","laser":["00","01"],"killedFigure":null},{"move":"72+1","laser":["79","78","77"],"killedFigure":null},{"move":"2435","laser":["00","01"],"killedFigure":null},{"move":"2837","laser":["79","78","77"],"killedFigure":null},{"move":"32+1","laser":["00","01"],"killedFigure":null},{"move":"73+1","laser":["79","78","77"],"killedFigure":null},{"move":"3242","laser":["00","01"],"killedFigure":null},{"move":"5948","laser":["79","78","77"],"killedFigure":null},{"move":"38+1","laser":["00","01"],"killedFigure":null},{"move":"3626","laser":["79","78","77"],"killedFigure":null},{"move":"3847","laser":["00","01"],"killedFigure":null},{"move":"37+1","laser":["79","78","77"],"killedFigure":null},{"move":"35+1","laser":["00","01"],"killedFigure":null},{"move":"6575","laser":["79","78","77"],"killedFigure":null},{"move":"35-1","laser":["00","01"],"killedFigure":null},{"move":"26+1","laser":["79","78","77"],"killedFigure":null},{"move":"35-1","laser":["00","01"],"killedFigure":null},{"move":"48+1","laser":["79","78","77"],"killedFigure":null},{"move":"4736","laser":["00","01"],"killedFigure":null},{"move":"7374","laser":["79","78","77"],"killedFigure":null},{"move":"3627","laser":["00","01"],"killedFigure":null},{"move":"75+1","laser":["79","78","77"],"killedFigure":null},{"move":"2717","laser":["00","01"],"killedFigure":null},{"move":"75+1","laser":["79","78","77"],"killedFigure":null},{"move":"3545","laser":["00","01"],"killedFigure":null},{"move":"7262","laser":["79","78","77"],"killedFigure":null},{"move":"4231","laser":["00","01"],"killedFigure":null},{"move":"5152","laser":["79","78","77"],"killedFigure":null},{"move":"3121","laser":["00","01"],"killedFigure":null},{"move":"44-1","laser":["79","78","77"],"killedFigure":null},{"move":"17-1","laser":["00","01"],"killedFigure":null},{"move":"4353","laser":["79","78","77"],"killedFigure":null},{"move":"2131","laser":["00","01"],"killedFigure":null},{"move":"2627","laser":["79","78","77"],"killedFigure":null},{"move":"3140","laser":["00","01"],"killedFigure":null},{"move":"74-1","laser":["79","78","77"],"killedFigure":null},{"move":"4534","laser":["00","01"],"killedFigure":null},{"move":"52+1","laser":["79","78","77"],"killedFigure":null},{"move":"3435","laser":["00","01"],"killedFigure":null},{"move":"7576","laser":["79","78","77"],"killedFigure":null},{"move":"3524","laser":["00","01"],"killedFigure":null}]}