[{"nickname":"aorgish","score":35,"id":3,"epamer":true,"language":"cs"},{"nickname":"qwerq","score":40.5,"id":2,"epamer":true,"language":"js"},{"nickname":"Thug","score":56.5,"id":4,"epamer":true,"language":"cs"},{"nickname":"c@biK","score":32,"id":5,"epamer":true,"language":"java"},{"nickname":"vacuk","score":5,"id":6,"epamer":true,"language":"java"},{"nickname":"Fryette","score":22,"id":7,"epamer":true,"language":"cs"},{"nickname":"x86","score":0,"id":8,"epamer":true,"language":""},{"nickname":"Darkus","score":0,"id":10,"epamer":false,"language":""},{"nickname":"Lesha","score":0,"id":11,"epamer":false,"language":""},{"nickname":"sergex","score":25,"id":12,"epamer":false,"language":"js"},{"nickname":"xBot","score":0,"id":15,"epamer":true,"language":""},{"nickname":"justsamter","score":0,"id":16,"epamer":false,"language":"js"},{"nickname":"quozd","score":0,"id":17,"epamer":true,"language":""},{"nickname":"redlabrat","score":0,"id":18,"epamer":false,"language":""},{"nickname":"Amphibian","score":69,"id":13,"epamer":true,"language":"cs"},{"nickname":"HAL9000","score":52,"id":14,"epamer":false,"language":"cs"},{"nickname":"Hancock","score":0,"id":19,"epamer":false,"language":"cs"},{"nickname":"Andrei Radkovich","score":0,"id":9,"epamer":true,"language":""},{"nickname":"noby256","score":0,"id":20,"epamer":false,"language":""},{"nickname":"scruoge","score":65,"id":22,"epamer":false,"language":"js"},{"nickname":"Chip","score":31.5,"id":23,"epamer":true,"language":"cs"},{"nickname":"Nikit_OS","score":0,"id":24,"epamer":false,"language":""},{"nickname":"Volans","score":0,"id":25,"epamer":false,"language":""},{"nickname":"aliaksandr_yarashuk","score":0,"id":26,"epamer":true,"language":""},{"nickname":"Zeratul","score":51,"id":61,"epamer":true,"language":"cs"},{"nickname":"aaaa","score":0,"id":27,"epamer":true,"language":""},{"nickname":"Alkion","score":0,"id":28,"epamer":true,"language":""},{"nickname":"Vovanella95","score":54,"id":30,"epamer":false,"language":"cs"},{"nickname":"noskill","score":77.5,"id":31,"epamer":true,"language":"cs"},{"nickname":"Perchik","score":76,"id":32,"epamer":true,"language":"cs"},{"nickname":"imarch","score":0,"id":33,"epamer":true,"language":""},{"nickname":"Mikhail15","score":40.5,"id":34,"epamer":false,"language":"cs"},{"nickname":"rushmash","score":36,"id":35,"epamer":false,"language":"java"},{"nickname":"Umnix","score":0,"id":38,"epamer":false,"language":""},{"nickname":"numitus2","score":73,"id":37,"epamer":true,"language":"java"},{"nickname":"nick","score":52,"id":40,"epamer":false,"language":"cs"},{"nickname":"Sheldon","score":71,"id":41,"epamer":true,"language":"cs"},{"nickname":"Blondeks","score":38.5,"id":42,"epamer":false,"language":"cs"},{"nickname":"g0ven","score":0,"id":43,"epamer":false,"language":""},{"nickname":"Pretender","score":46.5,"id":29,"epamer":true,"language":"java"},{"nickname":"dim-tim","score":0,"id":44,"epamer":true,"language":"java"},{"nickname":"Tymond","score":0,"id":45,"epamer":true,"language":""},{"nickname":"Yura","score":0,"id":46,"epamer":false,"language":""},{"nickname":"Ryzal","score":0,"id":47,"epamer":false,"language":""},{"nickname":"mished","score":0,"id":48,"epamer":true,"language":"cs"},{"nickname":"Dinozavr","score":0,"id":49,"epamer":false,"language":"cs"},{"nickname":"GoalkeeperBetterThanPerchik","score":76,"id":50,"epamer":true,"language":"cs"},{"nickname":"Flash","score":0,"id":51,"epamer":false,"language":"cs"},{"nickname":"Spoyke","score":0,"id":52,"epamer":false,"language":"cs"},{"nickname":"Sanych","score":36,"id":53,"epamer":false,"language":"cs"},{"nickname":"Maks","score":0,"id":54,"epamer":false,"language":""},{"nickname":"bort","score":0,"id":55,"epamer":false,"language":""},{"nickname":"Artwo-Deetwo","score":71,"id":56,"epamer":false,"language":"cs"},{"nickname":"asdf","score":0,"id":57,"epamer":false,"language":""},{"nickname":"Djejin","score":36,"id":58,"epamer":false,"language":"java"},{"nickname":"Djejin","score":0,"id":59,"epamer":false,"language":""},{"nickname":"archer","score":68,"id":60,"epamer":true,"language":"java"},{"nickname":"IMokin","score":55.5,"id":21,"epamer":false,"language":"cs"},{"nickname":"Vladl1313","score":63,"id":62,"epamer":false,"language":"cs"},{"nickname":"kodek.sh","score":58.5,"id":63,"epamer":false,"language":"java"},{"nickname":"octopus","score":0,"id":64,"epamer":true,"language":"cs"},{"nickname":"JutIgor","score":31,"id":65,"epamer":false,"language":"cs"},{"nickname":"Kwull","score":0,"id":66,"epamer":false,"language":""},{"nickname":"КАМАЛЕДИКАМКАМАЛЕДИЮМАЙБАТЕРФЛЯЙШУГАБЭЙБИ","score":0,"id":67,"epamer":false,"language":"js"},{"nickname":"eQual","score":69.5,"id":68,"epamer":false,"language":"cs"},{"nickname":"uk","score":23,"id":1,"epamer":true,"language":"cs"}]